<?xml version="1.0" encoding="utf-8" ?><dwsync><file name="php_tester.php" server="www.islavistahousing.com/islavistahousing.com/" local="3269701481" remote="2368053414742726360" /><file name="utilities.php" server="www.islavistahousing.com/islavistahousing.com/" local="3269703365" remote="2375259957548554544" /><file name="register.php" server="www.islavistahousing.com/islavistahousing.com/" local="3269995530" remote="2375983934416129688" /><file name="slick_bar2.png" server="www.chris-wilcox.com/islavistahousing.com/" local="3269595154" remote="2372888482766408232" /><file name="title.png" server="www.chris-wilcox.com/islavistahousing.com/" local="3269591997" remote="2372888482766408232" /><file name="utilities.php" server="www.chris-wilcox.com/islavistahousing.com/" local="3269703365" remote="2369823542564375080" /><file name="gradient.png" server="www.chris-wilcox.com/islavistahousing.com/" local="3269591857" remote="2369901384551647784" /><file name="php_tester.php" server="www.chris-wilcox.com/islavistahousing.com/" local="3269701481" remote="2369901384551647784" /><file name="register.php" server="www.chris-wilcox.com/islavistahousing.com/" local="3269995530" remote="2369901384551647784" /><file name="slick_bar.png" server="www.chris-wilcox.com/islavistahousing.com/" local="3269592735" remote="2369901384551647784" /><file name="slick_bar2.png" server="www.chris-wilcox.com/www/islavistahousing.com/" local="3269595154" remote="1975748370327325484" /><file name="title.png" server="www.chris-wilcox.com/www/islavistahousing.com/" local="3269591997" remote="1975748370327329084" /><file name="utilities.php" server="www.chris-wilcox.com/www/islavistahousing.com/" local="3269703365" remote="1980363913982148324" /><file name="gradient.png" server="www.chris-wilcox.com/www/islavistahousing.com/" local="3269591857" remote="2241791374924634428" /><file name="php_tester.php" server="www.chris-wilcox.com/www/islavistahousing.com/" local="3270013741" remote="1979144985083832440" /><file name="register.php" server="www.chris-wilcox.com/www/islavistahousing.com/" local="3270909594" remote="2632506164750199984" /><file name="slick_bar.png" server="www.chris-wilcox.com/www/islavistahousing.com/" local="3269592735" remote="1979144985083832440" /><file name="login.php" server="www.chris-wilcox.com/www/islavistahousing.com/" local="3270919775" remote="2630398761737016396" /><file name="confirm.php" server="www.chris-wilcox.com/www/islavistahousing.com/" local="3270909601" remote="2632506164750199984" /><file name="home.php" server="www.chris-wilcox.com/www/islavistahousing.com/" local="3271254097" remote="2243674322948025916" /><file name="logout.php" server="www.chris-wilcox.com/www/islavistahousing.com/" local="3270167114" remote="1979144985083832440" /><file name="checkcookie.php" server="www.chris-wilcox.com/www/islavistahousing.com/" local="3270169798" remote="2238456865395972472" /><file name="userbar.php" server="www.chris-wilcox.com/www/islavistahousing.com/" local="3270213421" remote="2238456865396320412" /><file name="index.php" server="www.chris-wilcox.com/www/islavistahousing.com/" local="3271209938" remote="1965495699277267388" /><file name="checkcookie_nofwd.php" server="www.chris-wilcox.com/www/islavistahousing.com/" local="3270169858" remote="2239507706454350200" /><file name="std_connect.php" server="www.chris-wilcox.com/www/islavistahousing.com/" local="3270169545" remote="2239507070799190392" /><file name="std_page.css" server="www.chris-wilcox.com/www/islavistahousing.com/" local="3271252344" remote="2238456865396320232" /><file name="std_page_top.php" server="www.chris-wilcox.com/www/islavistahousing.com/" local="3271211248" remote="2238456865396320412" /><file name="std_page_bottom.php" server="www.chris-wilcox.com/www/islavistahousing.com/" local="3270209189" remote="2238456865396320412" /><file name="checkcookie_noconfirm.php" server="www.chris-wilcox.com/www/islavistahousing.com/" local="3270170060" remote="1979144985083832440" /><file name="top_bar.png" server="www.chris-wilcox.com/www/islavistahousing.com/" local="3270212692" remote="2241791374924679848" /><file name="account.php" server="www.chris-wilcox.com/www/islavistahousing.com/" local="3271116835" remote="2168105575965611576" /><file name="help.php" server="www.chris-wilcox.com/www/islavistahousing.com/" local="3270219654" remote="2537426996249208220" /><file name="property.css" server="www.chris-wilcox.com/www/islavistahousing.com/" local="3271253158" remote="2235524983281117880" /><file name="property.php" server="www.chris-wilcox.com/www/islavistahousing.com/" local="3271253186" remote="2246855880102079160" /><file name="manage_properties.css" server="www.chris-wilcox.com/www/islavistahousing.com/" local="3270917914" remote="2344390567304514944" /><file name="manage_properties.php" server="www.chris-wilcox.com/www/islavistahousing.com/" local="3271047091" remote="1942187994093472340" /><file name="bg_left_menu.png" server="www.chris-wilcox.com/www/islavistahousing.com/" local="3270521546" remote="2241791374924988668" /><file name="map.php" server="www.chris-wilcox.com/www/islavistahousing.com/" local="3271054226" remote="2344711521620746632" /><file name="house_green.png" server="www.chris-wilcox.com/www/islavistahousing.com/" local="3270746403" remote="1962924096198258720" /><file name="house_red.png" server="www.chris-wilcox.com/www/islavistahousing.com/" local="3270746387" remote="411365116113825824" /><file name="property_db.php" server="www.chris-wilcox.com/www/islavistahousing.com/" local="3271251323" remote="1980999929920447348" /><file name="list.css" server="www.chris-wilcox.com/www/islavistahousing.com/" local="3271051103" remote="2238456865396118872" /><file name="list.php" server="www.chris-wilcox.com/www/islavistahousing.com/" local="3271258374" remote="2235707656830156572" /><file name="std_page_top_nomenu.php" server="www.chris-wilcox.com/www/islavistahousing.com/" local="3271006010" remote="1932612227068044628" /><file name="delete.png" server="www.chris-wilcox.com/www/islavistahousing.com/" local="3270311518" remote="2344390567304514944" /><file name="edit.gif" server="www.chris-wilcox.com/www/islavistahousing.com/" local="3270918362" remote="2344390567304515304" /><file name="view.gif" server="www.chris-wilcox.com/www/islavistahousing.com/" local="3270918599" remote="2238456865395986692" /><file name="map.gif" server="www.chris-wilcox.com/www/islavistahousing.com/" local="3270918812" remote="2238456865395986692" /><file name="map.css" server="www.chris-wilcox.com/www/islavistahousing.com/" local="3271052410" remote="1938987229845674684" /><file name="favicon.ico" server="www.chris-wilcox.com/www/islavistahousing.com/" local="3271114409" remote="414436378508086488" /><file name="guest_login.php" server="www.chris-wilcox.com/www/islavistahousing.com/" local="3271115254" remote="1943246119416451104" /><file name="pngfix.js" server="www.chris-wilcox.com/www/islavistahousing.com/" local="3271208053" remote="2235122716644130180" /><file name="image.php" server="www.chris-wilcox.com/www/islavistahousing.com/" local="3271247632" remote="2237503623174772008" /><file name="map.js" server="www.chris-wilcox.com/www/islavistahousing.com/" local="3271331857" remote="2211738732841443292" /></dwsync>